{"type": "Feature", "id": 12511928, "properties": {"woe:id": 12511928, "woe:parent_id": 1020985, "woe:name": "Pochentong Airport", "woe:placetype": 14, "woe:placetype_name": "Airport", "woe:lang": "ENG", "iso:country": "KH", "meta:provider": ["geoplanet:7.3.1", "geoplanet:7.3.2", "geoplanet:7.4.0", "geoplanet:7.4.1", "geoplanet:7.5.1", "geoplanet:7.5.2", "geoplanet:7.6.0", "geoplanet:7.8.1", "geoplanet:7.9.0", "geoplanet:7.10.0", "geoplanet:8.0.0", "woeplanet:8.0.0"], "meta:indexed": "2020-08-20T20:58:45.991474", "woe:alias_ENG_V": ["PNH Airport", "PNH"], "meta:updated": "2020-08-22T02:50:53.561716", "woe:hierarchy": {"continent": 24865671, "country": 23424776, "town": 0, "planet": 1, "county": 56063385, "suburb": 0, "state": 20070095, "region": 0, "localadmin": 0}, "woe:timezone_id": 28350847, "woe:hash": "w6499vug5m5g", "woe:centroid": [104.849197, 11.5458], "geom:latitude": 11.5458, "geom:longitude": 104.849197, "geom:hash": "w6499vug5m5g", "woe:latitude": 11.5458, "geom:centroid": [104.849197, 11.5458], "woe:longitude": 104.849197, "woe:repo": "woeplanet-airport-kh"}, "geometry": {"coordinates": [104.849197, 11.5458], "type": "Point"}}